CHANGES.txt
README.txt
bootstrap.py
buildout.cfg
setup.py
src/zope/__init__.py
src/zope.app.debugskin.egg-info/PKG-INFO
src/zope.app.debugskin.egg-info/SOURCES.txt
src/zope.app.debugskin.egg-info/dependency_links.txt
src/zope.app.debugskin.egg-info/namespace_packages.txt
src/zope.app.debugskin.egg-info/not-zip-safe
src/zope.app.debugskin.egg-info/requires.txt
src/zope.app.debugskin.egg-info/top_level.txt
src/zope/app/__init__.py
src/zope/app/debugskin/SETUP.cfg
src/zope/app/debugskin/__init__.py
src/zope/app/debugskin/configure.zcml
src/zope/app/debugskin/debugskin-configure.zcml
src/zope/app/debugskin/error_debug.pt
src/zope/app/debugskin/exceptions.py
src/zope/app/debugskin/ftesting.zcml
src/zope/app/debugskin/testing.py
src/zope/app/debugskin/tests.py
src/zope/app/debugskin/unauthorized.pt